dogpile_cache_cachetools/__init__.py
dogpile_cache_cachetools-0.0.2.dist-info/DESCRIPTION.rst
dogpile_cache_cachetools-0.0.2.dist-info/METADATA
dogpile_cache_cachetools-0.0.2.dist-info/RECORD
dogpile_cache_cachetools-0.0.2.dist-info/WHEEL
dogpile_cache_cachetools-0.0.2.dist-info/metadata.json
dogpile_cache_cachetools-0.0.2.dist-info/top_level.txt
