Metadata-Version: 2.0
Name: dogpile-cache-cachetools
Version: 0.0.2
Summary: cachetool backends of dogpile.cache
Home-page: https://github.com/manthey
Author: Kitware, Inc.
Author-email: kitware@kitware.com
License: Apache Software License 2.0
Keywords: dogpile.cache cachetools
Platform: UNKNOWN
Classifier: Development Status :: 3 - Alpha
Classifier: License :: OSI Approved :: Apache Software License
Classifier: Natural Language :: English
Classifier: Programming Language :: Python :: 2
Classifier: Programming Language :: Python :: 2.7
Classifier: Programming Language :: Python :: 3
Classifier: Programming Language :: Python :: 3.4
Classifier: Programming Language :: Python :: 3.5
Classifier: Programming Language :: Python :: 3.6
Classifier: Programming Language :: Python :: 3.7
Requires-Dist: cachetools (>=3.0.0)
Requires-Dist: dogpile.cache (>=0.7.1)
